[
    {
        "region": "전국",
        "link": "http://ncov.mohw.go.kr/bdBoardList_Real.do?brdGubun=13",
        "confirmed": 22783,
        "confirmed_delta": 126,
        "recovered": 19771,
        "deaths": 377,
        "confirmed_rate": 43.94,
        "confirmed_region_rate": "",
        "confirmed_region_class": ""
    },
    {
        "region": "서울",
        "link": "http://www.seoul.go.kr/coronaV/coronaStatus.do",
        "confirmed": 4904,
        "confirmed_delta": 46,
        "recovered": 3841,
        "deaths": 46,
        "confirmed_rate": 50.38,
        "confirmed_region_rate": 21.52,
        "confirmed_region_class": "moderate"
    },
    {
        "region": "부산",
        "link": "http://www.busan.go.kr/corona19/index",
        "confirmed": 369,
        "confirmed_delta": 2,
        "recovered": 311,
        "deaths": 4,
        "confirmed_rate": 10.82,
        "confirmed_region_rate": 1.62,
        "confirmed_region_class": "mild"
    },
    {
        "region": "대구",
        "link": "http://www.daegu.go.kr/",
        "confirmed": 7120,
        "confirmed_delta": 2,
        "recovered": 6859,
        "deaths": 192,
        "confirmed_rate": 292.22,
        "confirmed_region_rate": 31.25,
        "confirmed_region_class": "severe"
    },
    {
        "region": "인천",
        "link": "https://www.incheon.go.kr/",
        "confirmed": 865,
        "confirmed_delta": 6,
        "recovered": 738,
        "deaths": 8,
        "confirmed_rate": 29.26,
        "confirmed_region_rate": 3.8,
        "confirmed_region_class": "mild"
    },
    {
        "region": "광주",
        "link": "https://www.gwangju.go.kr/",
        "confirmed": 485,
        "confirmed_delta": 0,
        "recovered": 400,
        "deaths": 3,
        "confirmed_rate": 33.29,
        "confirmed_region_rate": 2.13,
        "confirmed_region_class": "mild"
    },
    {
        "region": "대전",
        "link": "https://www.daejeon.go.kr/corona19/index.do",
        "confirmed": 350,
        "confirmed_delta": 3,
        "recovered": 287,
        "deaths": 3,
        "confirmed_rate": 23.74,
        "confirmed_region_rate": 1.54,
        "confirmed_region_class": "mild"
    },
    {
        "region": "울산",
        "link": "http://www.ulsan.go.kr/corona.jsp",
        "confirmed": 141,
        "confirmed_delta": 0,
        "recovered": 108,
        "deaths": 1,
        "confirmed_rate": 12.29,
        "confirmed_region_rate": 0.62,
        "confirmed_region_class": "mild"
    },
    {
        "region": "세종",
        "link": "https://www.sejong.go.kr/life/sub05_0704.do",
        "confirmed": 70,
        "confirmed_delta": 0,
        "recovered": 64,
        "deaths": 0,
        "confirmed_rate": 20.45,
        "confirmed_region_rate": 0.31,
        "confirmed_region_class": "mild"
    },
    {
        "region": "경기",
        "link": "https://www.gg.go.kr/bbs/boardView.do?bsIdx=464&bIdx=2296956&menuId=1535",
        "confirmed": 4089,
        "confirmed_delta": 37,
        "recovered": 3296,
        "deaths": 59,
        "confirmed_rate": 30.86,
        "confirmed_region_rate": 17.95,
        "confirmed_region_class": "moderate"
    },
    {
        "region": "강원",
        "link": "http://www.provin.gangwon.kr/",
        "confirmed": 217,
        "confirmed_delta": 0,
        "recovered": 188,
        "deaths": 3,
        "confirmed_rate": 14.09,
        "confirmed_region_rate": 0.95,
        "confirmed_region_class": "mild"
    },
    {
        "region": "충북",
        "link": "http://www.chungbuk.go.kr/",
        "confirmed": 154,
        "confirmed_delta": 3,
        "recovered": 126,
        "deaths": 1,
        "confirmed_rate": 9.63,
        "confirmed_region_rate": 0.68,
        "confirmed_region_class": "mild"
    },
    {
        "region": "충남",
        "link": "http://www.chungnam.go.kr/coronaStatus.do",
        "confirmed": 463,
        "confirmed_delta": 6,
        "recovered": 335,
        "deaths": 2,
        "confirmed_rate": 21.81,
        "confirmed_region_rate": 2.03,
        "confirmed_region_class": "mild"
    },
    {
        "region": "전북",
        "link": "http://www.jeonbuk.go.kr/",
        "confirmed": 114,
        "confirmed_delta": 8,
        "recovered": 79,
        "deaths": 0,
        "confirmed_rate": 6.27,
        "confirmed_region_rate": 0.5,
        "confirmed_region_class": "mild"
    },
    {
        "region": "전남",
        "link": "https://www.jeonnam.go.kr/coronaMainPage.do",
        "confirmed": 167,
        "confirmed_delta": 0,
        "recovered": 100,
        "deaths": 0,
        "confirmed_rate": 8.96,
        "confirmed_region_rate": 0.73,
        "confirmed_region_class": "mild"
    },
    {
        "region": "경북",
        "link": "http://gb.go.kr/corona_main.htm",
        "confirmed": 1502,
        "confirmed_delta": 5,
        "recovered": 1407,
        "deaths": 55,
        "confirmed_rate": 56.41,
        "confirmed_region_rate": 6.59,
        "confirmed_region_class": "mild"
    },
    {
        "region": "경남",
        "link": "http://www.gyeongnam.go.kr/corona.html",
        "confirmed": 281,
        "confirmed_delta": 4,
        "recovered": 246,
        "deaths": 0,
        "confirmed_rate": 8.36,
        "confirmed_region_rate": 1.23,
        "confirmed_region_class": "mild"
    },
    {
        "region": "제주",
        "link": "https://jeju.go.kr/covid19.jsp",
        "confirmed": 58,
        "confirmed_delta": 2,
        "recovered": 45,
        "deaths": 0,
        "confirmed_rate": 8.65,
        "confirmed_region_rate": 0.25,
        "confirmed_region_class": "none"
    }
]