[
    {
        "Name": "미국",
        "Name_ch": "美国",
        "Name_en": "United States",
        "confirmed": 7435016,
        "deaths": 211458,
        "recovered": 4679362
    },
    {
        "Name": "인도",
        "Name_ch": "印度",
        "Name_en": "India",
        "confirmed": 6310267,
        "deaths": 98708,
        "recovered": 5270007
    },
    {
        "Name": "브라질",
        "Name_ch": "巴西",
        "Name_en": "Brazil",
        "confirmed": 4787637,
        "deaths": 143243,
        "recovered": 4135088
    },
    {
        "Name": "러시아",
        "Name_ch": "俄罗斯",
        "Name_en": "Russia",
        "confirmed": 1176286,
        "deaths": 20722,
        "recovered": 958257
    },
    {
        "Name": "콜롬비아",
        "Name_ch": "哥伦比亚",
        "Name_en": "Colombia",
        "confirmed": 824042,
        "deaths": 25828,
        "recovered": 734154
    },
    {
        "Name": "페루",
        "Name_ch": "秘鲁",
        "Name_en": "Peru",
        "confirmed": 811768,
        "deaths": 32396,
        "recovered": 676925
    },
    {
        "Name": "스페인",
        "Name_ch": "西班牙",
        "Name_en": "Spain",
        "confirmed": 769188,
        "deaths": 31791,
        "recovered": 0
    },
    {
        "Name": "멕시코",
        "Name_ch": "墨西哥",
        "Name_en": "Mexico",
        "confirmed": 738163,
        "deaths": 77163,
        "recovered": 530945
    },
    {
        "Name": "Argentina",
        "Name_ch": "",
        "Name_en": "Argentina",
        "confirmed": 736609,
        "deaths": 16519,
        "recovered": 585857
    },
    {
        "Name": "남아프리카 공화국",
        "Name_ch": "南非共和国",
        "Name_en": "South Africa",
        "confirmed": 672572,
        "deaths": 16667,
        "recovered": 606520
    },
    {
        "Name": "프랑스",
        "Name_ch": "法国",
        "Name_en": "France",
        "confirmed": 563535,
        "deaths": 31956,
        "recovered": 96797
    },
    {
        "Name": "칠레",
        "Name_ch": "智利",
        "Name_en": "Chile",
        "confirmed": 462991,
        "deaths": 12741,
        "recovered": 436589
    },
    {
        "Name": "이란",
        "Name_ch": "伊朗",
        "Name_en": "Iran",
        "confirmed": 457219,
        "deaths": 26169,
        "recovered": 380956
    },
    {
        "Name": "영국",
        "Name_ch": "英国",
        "Name_en": "UK",
        "confirmed": 453264,
        "deaths": 42143,
        "recovered": 0
    },
    {
        "Name": "Bangladesh",
        "Name_ch": "",
        "Name_en": "Bangladesh",
        "confirmed": 363479,
        "deaths": 5251,
        "recovered": 275487
    },
    {
        "Name": "이라크",
        "Name_ch": "伊拉克",
        "Name_en": "Iraq",
        "confirmed": 362981,
        "deaths": 9181,
        "recovered": 292197
    },
    {
        "Name": "사우디아라비아",
        "Name_ch": "沙特阿拉伯",
        "Name_en": "Saudi Arabia",
        "confirmed": 334605,
        "deaths": 4768,
        "recovered": 319154
    },
    {
        "Name": "터키",
        "Name_ch": "土耳其",
        "Name_en": "Turkey",
        "confirmed": 318663,
        "deaths": 8195,
        "recovered": 279749
    },
    {
        "Name": "이탈리아",
        "Name_ch": "义大利",
        "Name_en": "Italy",
        "confirmed": 314861,
        "deaths": 35894,
        "recovered": 227704
    },
    {
        "Name": "파키스탄",
        "Name_ch": "巴基斯坦",
        "Name_en": "Pakistan",
        "confirmed": 312263,
        "deaths": 6479,
        "recovered": 296881
    },
    {
        "Name": "필리핀",
        "Name_ch": "菲律宾",
        "Name_en": "Philippines",
        "confirmed": 311694,
        "deaths": 5504,
        "recovered": 253488
    },
    {
        "Name": "독일",
        "Name_ch": "德国",
        "Name_en": "Germany",
        "confirmed": 292896,
        "deaths": 9571,
        "recovered": 256000
    },
    {
        "Name": "인도네시아",
        "Name_ch": "印度尼西亚",
        "Name_en": "Indonesia",
        "confirmed": 287008,
        "deaths": 10740,
        "recovered": 214947
    },
    {
        "Name": "이스라엘",
        "Name_ch": "以色列",
        "Name_en": "Israel",
        "confirmed": 245494,
        "deaths": 1569,
        "recovered": 174506
    },
    {
        "Name": "Ukraine",
        "Name_ch": "",
        "Name_en": "Ukraine",
        "confirmed": 208959,
        "deaths": 4129,
        "recovered": 92360
    },
    {
        "Name": "캐나다",
        "Name_ch": "加拿大",
        "Name_en": "Canada",
        "confirmed": 158425,
        "deaths": 9295,
        "recovered": 134194
    },
    {
        "Name": "에콰도르",
        "Name_ch": "厄瓜多尔",
        "Name_en": "Ecuador",
        "confirmed": 137047,
        "deaths": 11355,
        "recovered": 112296
    },
    {
        "Name": "Bolivia",
        "Name_ch": "",
        "Name_en": "Bolivia",
        "confirmed": 134641,
        "deaths": 7931,
        "recovered": 94895
    },
    {
        "Name": "루마니아",
        "Name_ch": "尼亚",
        "Name_en": "Romania",
        "confirmed": 127572,
        "deaths": 4825,
        "recovered": 102476
    },
    {
        "Name": "카타르",
        "Name_ch": "卡塔尔",
        "Name_en": "Qatar",
        "confirmed": 125760,
        "deaths": 214,
        "recovered": 122699
    },
    {
        "Name": "모로코",
        "Name_ch": "摩洛哥",
        "Name_en": "Morocco",
        "confirmed": 123653,
        "deaths": 2194,
        "recovered": 102715
    },
    {
        "Name": "네덜란드",
        "Name_ch": "荷兰",
        "Name_en": "Netherlands",
        "confirmed": 120845,
        "deaths": 6406,
        "recovered": 0
    },
    {
        "Name": "벨기에",
        "Name_ch": "比利时",
        "Name_en": "Belgium",
        "confirmed": 117115,
        "deaths": 10001,
        "recovered": 19386
    },
    {
        "Name": "도미니카 공화국",
        "Name_ch": "多明尼加共和国",
        "Name_en": "Dominican Republic",
        "confirmed": 112209,
        "deaths": 2105,
        "recovered": 87629
    },
    {
        "Name": "Panama",
        "Name_ch": "",
        "Name_en": "Panama",
        "confirmed": 111853,
        "deaths": 2364,
        "recovered": 88202
    },
    {
        "Name": "Kazakhstan",
        "Name_ch": "",
        "Name_en": "Kazakhstan",
        "confirmed": 107908,
        "deaths": 1725,
        "recovered": 102874
    },
    {
        "Name": "쿠웨이트",
        "Name_ch": "科威特",
        "Name_en": "Kuwait",
        "confirmed": 105182,
        "deaths": 610,
        "recovered": 96688
    },
    {
        "Name": "이집트",
        "Name_ch": "埃及",
        "Name_en": "Egypt",
        "confirmed": 103079,
        "deaths": 5914,
        "recovered": 96094
    },
    {
        "Name": "오만",
        "Name_ch": "阿曼",
        "Name_en": "Oman",
        "confirmed": 98585,
        "deaths": 935,
        "recovered": 88528
    },
    {
        "Name": "아랍에미리트",
        "Name_ch": "阿拉伯联合酋长国",
        "Name_en": "UAE",
        "confirmed": 94190,
        "deaths": 419,
        "recovered": 83724
    },
    {
        "Name": "스웨덴",
        "Name_ch": "瑞典语",
        "Name_en": "Sweden",
        "confirmed": 92863,
        "deaths": 5893,
        "recovered": 0
    },
    {
        "Name": "Guatemala",
        "Name_ch": "",
        "Name_en": "Guatemala",
        "confirmed": 91746,
        "deaths": 3246,
        "recovered": 80256
    },
    {
        "Name": "폴란드",
        "Name_ch": "波兰",
        "Name_en": "Poland",
        "confirmed": 91514,
        "deaths": 2513,
        "recovered": 69695
    },
    {
        "Name": "일본",
        "Name_ch": "日本",
        "Name_en": "Japan",
        "confirmed": 82494,
        "deaths": 1557,
        "recovered": 75459
    },
    {
        "Name": "벨라루스",
        "Name_ch": "白俄罗斯",
        "Name_en": "Belarus",
        "confirmed": 78631,
        "deaths": 833,
        "recovered": 74525
    },
    {
        "Name": "네팔",
        "Name_ch": "尼泊尔",
        "Name_en": "Nepal",
        "confirmed": 77817,
        "deaths": 498,
        "recovered": 56428
    },
    {
        "Name": "Honduras",
        "Name_ch": "",
        "Name_en": "Honduras",
        "confirmed": 76098,
        "deaths": 2323,
        "recovered": 27383
    },
    {
        "Name": "코스타리카",
        "Name_ch": "哥斯达黎加",
        "Name_en": "Costa Rica",
        "confirmed": 75760,
        "deaths": 904,
        "recovered": 37841
    },
    {
        "Name": "포르투갈",
        "Name_ch": "葡萄牙",
        "Name_en": "Portugal",
        "confirmed": 75542,
        "deaths": 1971,
        "recovered": 48530
    },
    {
        "Name": "Ethiopia",
        "Name_ch": "",
        "Name_en": "Ethiopia",
        "confirmed": 75368,
        "deaths": 1198,
        "recovered": 31204
    },
    {
        "Name": "Venezuela",
        "Name_ch": "",
        "Name_en": "Venezuela",
        "confirmed": 74363,
        "deaths": 621,
        "recovered": 64200
    },
    {
        "Name": "바레인",
        "Name_ch": "巴林",
        "Name_en": "Bahrain",
        "confirmed": 70422,
        "deaths": 248,
        "recovered": 64267
    },
    {
        "Name": "체코",
        "Name_ch": "捷克",
        "Name_en": "Czechia",
        "confirmed": 68919,
        "deaths": 655,
        "recovered": 33443
    },
    {
        "Name": "나이지리아",
        "Name_ch": "尼日利亚",
        "Name_en": "Nigeria",
        "confirmed": 58647,
        "deaths": 1111,
        "recovered": 49937
    },
    {
        "Name": "싱가포르",
        "Name_ch": "新加坡",
        "Name_en": "Singapore",
        "confirmed": 57765,
        "deaths": 27,
        "recovered": 57488
    },
    {
        "Name": "Uzbekistan",
        "Name_ch": "",
        "Name_en": "Uzbekistan",
        "confirmed": 56717,
        "deaths": 470,
        "recovered": 53366
    },
    {
        "Name": "스위스",
        "Name_ch": "瑞士",
        "Name_en": "Switzerland",
        "confirmed": 53282,
        "deaths": 2074,
        "recovered": 42700
    },
    {
        "Name": "Moldova",
        "Name_ch": "",
        "Name_en": "Moldova",
        "confirmed": 53042,
        "deaths": 1320,
        "recovered": 38997
    },
    {
        "Name": "알제리",
        "Name_ch": "阿尔及利亚",
        "Name_en": "Algeria",
        "confirmed": 51530,
        "deaths": 1736,
        "recovered": 36174
    },
    {
        "Name": "아르메니아",
        "Name_ch": "亚美尼亚",
        "Name_en": "Armenia",
        "confirmed": 50359,
        "deaths": 959,
        "recovered": 44001
    },
    {
        "Name": "Kyrgyzstan",
        "Name_ch": "",
        "Name_en": "Kyrgyzstan",
        "confirmed": 46669,
        "deaths": 1064,
        "recovered": 42879
    },
    {
        "Name": "Ghana",
        "Name_ch": "",
        "Name_en": "Ghana",
        "confirmed": 46482,
        "deaths": 301,
        "recovered": 45651
    },
    {
        "Name": "오스트리아",
        "Name_ch": "奥地利",
        "Name_en": "Austria",
        "confirmed": 44813,
        "deaths": 799,
        "recovered": 35644
    },
    {
        "Name": "아제르바이잔",
        "Name_ch": "阿塞拜疆",
        "Name_en": "Azerbaijan",
        "confirmed": 40229,
        "deaths": 591,
        "recovered": 37954
    },
    {
        "Name": "Paraguay",
        "Name_ch": "",
        "Name_en": "Paraguay",
        "confirmed": 40101,
        "deaths": 841,
        "recovered": 23748
    },
    {
        "Name": "팔레스타인",
        "Name_ch": "巴勒斯坦",
        "Name_en": "Palestine",
        "confirmed": 39899,
        "deaths": 311,
        "recovered": 31743
    },
    {
        "Name": "레바논",
        "Name_ch": "黎巴嫩",
        "Name_en": "Lebanon",
        "confirmed": 39634,
        "deaths": 367,
        "recovered": 17565
    },
    {
        "Name": "아프가니스탄",
        "Name_ch": "阿富汗",
        "Name_en": "Afghanistan",
        "confirmed": 39268,
        "deaths": 1458,
        "recovered": 32789
    },
    {
        "Name": "Kenya",
        "Name_ch": "",
        "Name_en": "Kenya",
        "confirmed": 38529,
        "deaths": 711,
        "recovered": 24908
    },
    {
        "Name": "아일랜드",
        "Name_ch": "冰岛",
        "Name_en": "Ireland",
        "confirmed": 36155,
        "deaths": 1804,
        "recovered": 23364
    },
    {
        "Name": "Libya",
        "Name_ch": "",
        "Name_en": "Libya",
        "confirmed": 34525,
        "deaths": 551,
        "recovered": 19361
    },
    {
        "Name": "세르비아",
        "Name_ch": "塞尔维亚",
        "Name_en": "Serbia",
        "confirmed": 33551,
        "deaths": 749,
        "recovered": 31536
    },
    {
        "Name": "El Salvador",
        "Name_ch": "",
        "Name_en": "El Salvador",
        "confirmed": 29077,
        "deaths": 843,
        "recovered": 23813
    },
    {
        "Name": "덴마크",
        "Name_ch": "丹麦",
        "Name_en": "Denmark",
        "confirmed": 27998,
        "deaths": 650,
        "recovered": 20754
    },
    {
        "Name": "보스니아 헤르체고비나",
        "Name_ch": "波斯尼亚和黑塞哥维那",
        "Name_en": "Bosnia and Herzegovina",
        "confirmed": 27469,
        "deaths": 856,
        "recovered": 20616
    },
    {
        "Name": "호주",
        "Name_ch": "澳大利亚",
        "Name_en": "Australia",
        "confirmed": 27078,
        "deaths": 886,
        "recovered": 24754
    },
    {
        "Name": "헝가리",
        "Name_ch": "匈牙利",
        "Name_en": "Hungary",
        "confirmed": 26461,
        "deaths": 765,
        "recovered": 5890
    },
    {
        "Name": "카메룬",
        "Name_ch": "喀麦隆",
        "Name_en": "Cameroon",
        "confirmed": 20838,
        "deaths": 418,
        "recovered": 19440
    },
    {
        "Name": "Bulgaria",
        "Name_ch": "",
        "Name_en": "Bulgaria",
        "confirmed": 20547,
        "deaths": 813,
        "recovered": 14489
    },
    {
        "Name": "Ivory Coast",
        "Name_ch": "",
        "Name_en": "Ivory Coast",
        "confirmed": 19669,
        "deaths": 120,
        "recovered": 19241
    },
    {
        "Name": "그리스",
        "Name_ch": "希腊",
        "Name_en": "Greece",
        "confirmed": 18475,
        "deaths": 391,
        "recovered": 9989
    },
    {
        "Name": "Tunisia",
        "Name_ch": "",
        "Name_en": "Tunisia",
        "confirmed": 18413,
        "deaths": 265,
        "recovered": 5032
    },
    {
        "Name": "North Macedonia",
        "Name_ch": "",
        "Name_en": "North Macedonia",
        "confirmed": 17977,
        "deaths": 739,
        "recovered": 14959
    },
    {
        "Name": "크로아티아",
        "Name_ch": "克罗地亚",
        "Name_en": "Croatia",
        "confirmed": 16593,
        "deaths": 280,
        "recovered": 15057
    },
    {
        "Name": "Madagascar",
        "Name_ch": "",
        "Name_en": "Madagascar",
        "confirmed": 16408,
        "deaths": 230,
        "recovered": 15301
    },
    {
        "Name": "세네갈",
        "Name_ch": "塞内加尔",
        "Name_en": "Senegal",
        "confirmed": 14982,
        "deaths": 311,
        "recovered": 12437
    },
    {
        "Name": "Zambia",
        "Name_ch": "",
        "Name_en": "Zambia",
        "confirmed": 14759,
        "deaths": 332,
        "recovered": 13959
    },
    {
        "Name": "노르웨이",
        "Name_ch": "挪威",
        "Name_en": "Norway",
        "confirmed": 13961,
        "deaths": 274,
        "recovered": 11190
    },
    {
        "Name": "Albania",
        "Name_ch": "",
        "Name_en": "Albania",
        "confirmed": 13649,
        "deaths": 387,
        "recovered": 7847
    },
    {
        "Name": "Sudan",
        "Name_ch": "",
        "Name_en": "Sudan",
        "confirmed": 13640,
        "deaths": 836,
        "recovered": 6764
    },
    {
        "Name": "Myanmar",
        "Name_ch": "",
        "Name_en": "Myanmar",
        "confirmed": 13373,
        "deaths": 310,
        "recovered": 3755
    },
    {
        "Name": "요르단",
        "Name_ch": "约旦",
        "Name_en": "Jordan",
        "confirmed": 11825,
        "deaths": 61,
        "recovered": 4626
    },
    {
        "Name": "Namibia",
        "Name_ch": "",
        "Name_en": "Namibia",
        "confirmed": 11265,
        "deaths": 121,
        "recovered": 9014
    },
    {
        "Name": "말레이시아",
        "Name_ch": "马来西亚",
        "Name_en": "Malaysia",
        "confirmed": 11224,
        "deaths": 136,
        "recovered": 9967
    },
    {
        "Name": "Montenegro",
        "Name_ch": "",
        "Name_en": "Montenegro",
        "confirmed": 10772,
        "deaths": 169,
        "recovered": 7192
    },
    {
        "Name": "DRC",
        "Name_ch": "",
        "Name_en": "DRC",
        "confirmed": 10659,
        "deaths": 272,
        "recovered": 10139
    },
    {
        "Name": "Guinea",
        "Name_ch": "",
        "Name_en": "Guinea",
        "confirmed": 10634,
        "deaths": 66,
        "recovered": 9960
    },
    {
        "Name": "Maldives",
        "Name_ch": "",
        "Name_en": "Maldives",
        "confirmed": 10291,
        "deaths": 34,
        "recovered": 9108
    },
    {
        "Name": "슬로바키아",
        "Name_ch": "斯洛伐克",
        "Name_en": "Slovakia",
        "confirmed": 10141,
        "deaths": 48,
        "recovered": 4395
    },
    {
        "Name": "핀란드",
        "Name_ch": "芬兰",
        "Name_en": "Finland",
        "confirmed": 9992,
        "deaths": 344,
        "recovered": 8100
    },
    {
        "Name": "French Guiana",
        "Name_ch": "",
        "Name_en": "French Guiana",
        "confirmed": 9955,
        "deaths": 66,
        "recovered": 9589
    },
    {
        "Name": "Tajikistan",
        "Name_ch": "",
        "Name_en": "Tajikistan",
        "confirmed": 9769,
        "deaths": 76,
        "recovered": 8572
    },
    {
        "Name": "Haiti",
        "Name_ch": "",
        "Name_en": "Haiti",
        "confirmed": 8766,
        "deaths": 229,
        "recovered": 6829
    },
    {
        "Name": "Gabon",
        "Name_ch": "",
        "Name_en": "Gabon",
        "confirmed": 8752,
        "deaths": 54,
        "recovered": 7955
    },
    {
        "Name": "Mozambique",
        "Name_ch": "",
        "Name_en": "Mozambique",
        "confirmed": 8728,
        "deaths": 61,
        "recovered": 5232
    },
    {
        "Name": "룩셈부르크",
        "Name_ch": "卢森堡",
        "Name_en": "Luxembourg",
        "confirmed": 8509,
        "deaths": 124,
        "recovered": 7174
    },
    {
        "Name": "Uganda",
        "Name_ch": "",
        "Name_en": "Uganda",
        "confirmed": 8129,
        "deaths": 75,
        "recovered": 4260
    },
    {
        "Name": "Zimbabwe",
        "Name_ch": "",
        "Name_en": "Zimbabwe",
        "confirmed": 7837,
        "deaths": 228,
        "recovered": 6122
    },
    {
        "Name": "Mauritania",
        "Name_ch": "",
        "Name_en": "Mauritania",
        "confirmed": 7488,
        "deaths": 161,
        "recovered": 7111
    },
    {
        "Name": "Jamaica",
        "Name_ch": "",
        "Name_en": "Jamaica",
        "confirmed": 6482,
        "deaths": 107,
        "recovered": 1867
    },
    {
        "Name": "조지아",
        "Name_ch": "格鲁吉亚",
        "Name_en": "Georgia",
        "confirmed": 6192,
        "deaths": 39,
        "recovered": 3120
    },
    {
        "Name": "Cabo Verde",
        "Name_ch": "",
        "Name_en": "Cabo Verde",
        "confirmed": 6024,
        "deaths": 60,
        "recovered": 5277
    },
    {
        "Name": "Malawi",
        "Name_ch": "",
        "Name_en": "Malawi",
        "confirmed": 5773,
        "deaths": 179,
        "recovered": 4263
    },
    {
        "Name": "슬로베니아",
        "Name_ch": "斯洛文尼亚",
        "Name_en": "Slovenia",
        "confirmed": 5690,
        "deaths": 150,
        "recovered": 3804
    },
    {
        "Name": "Cuba",
        "Name_ch": "",
        "Name_en": "Cuba",
        "confirmed": 5597,
        "deaths": 122,
        "recovered": 4893
    },
    {
        "Name": "Guadeloupe",
        "Name_ch": "",
        "Name_en": "Guadeloupe",
        "confirmed": 5528,
        "deaths": 57,
        "recovered": 2199
    },
    {
        "Name": "Eswatini",
        "Name_ch": "",
        "Name_en": "Eswatini",
        "confirmed": 5482,
        "deaths": 109,
        "recovered": 4912
    },
    {
        "Name": "Djibouti",
        "Name_ch": "",
        "Name_en": "Djibouti",
        "confirmed": 5416,
        "deaths": 61,
        "recovered": 5344
    },
    {
        "Name": "Nicaragua",
        "Name_ch": "",
        "Name_en": "Nicaragua",
        "confirmed": 5170,
        "deaths": 151,
        "recovered": 2913
    },
    {
        "Name": "홍콩",
        "Name_ch": "香港",
        "Name_en": "Hong Kong",
        "confirmed": 5088,
        "deaths": 105,
        "recovered": 4827
    },
    {
        "Name": "Equatorial Guinea",
        "Name_ch": "",
        "Name_en": "Equatorial Guinea",
        "confirmed": 5030,
        "deaths": 83,
        "recovered": 4769
    },
    {
        "Name": "Congo",
        "Name_ch": "",
        "Name_en": "Congo",
        "confirmed": 5008,
        "deaths": 89,
        "recovered": 3887
    },
    {
        "Name": "Angola",
        "Name_ch": "",
        "Name_en": "Angola",
        "confirmed": 4972,
        "deaths": 183,
        "recovered": 1941
    },
    {
        "Name": "Suriname",
        "Name_ch": "",
        "Name_en": "Suriname",
        "confirmed": 4863,
        "deaths": 104,
        "recovered": 4676
    },
    {
        "Name": "Rwanda",
        "Name_ch": "",
        "Name_en": "Rwanda",
        "confirmed": 4836,
        "deaths": 29,
        "recovered": 3125
    },
    {
        "Name": "CAR",
        "Name_ch": "",
        "Name_en": "CAR",
        "confirmed": 4806,
        "deaths": 62,
        "recovered": 1840
    },
    {
        "Name": "Lithuania",
        "Name_ch": "",
        "Name_en": "Lithuania",
        "confirmed": 4693,
        "deaths": 92,
        "recovered": 2365
    },
    {
        "Name": "Trinidad and Tobago",
        "Name_ch": "",
        "Name_en": "Trinidad and Tobago",
        "confirmed": 4517,
        "deaths": 75,
        "recovered": 2560
    },
    {
        "Name": "Syria",
        "Name_ch": "",
        "Name_en": "Syria",
        "confirmed": 4148,
        "deaths": 197,
        "recovered": 1088
    },
    {
        "Name": "Bahamas",
        "Name_ch": "",
        "Name_en": "Bahamas",
        "confirmed": 4022,
        "deaths": 95,
        "recovered": 2141
    },
    {
        "Name": "Réunion",
        "Name_ch": "",
        "Name_en": "Réunion",
        "confirmed": 3993,
        "deaths": 16,
        "recovered": 2819
    },
    {
        "Name": "Aruba",
        "Name_ch": "",
        "Name_en": "Aruba",
        "confirmed": 3934,
        "deaths": 26,
        "recovered": 3181
    },
    {
        "Name": "Mayotte",
        "Name_ch": "",
        "Name_en": "Mayotte",
        "confirmed": 3779,
        "deaths": 42,
        "recovered": 2964
    },
    {
        "Name": "Somalia",
        "Name_ch": "",
        "Name_en": "Somalia",
        "confirmed": 3588,
        "deaths": 99,
        "recovered": 2946
    },
    {
        "Name": "Gambia",
        "Name_ch": "",
        "Name_en": "Gambia",
        "confirmed": 3579,
        "deaths": 112,
        "recovered": 2161
    },
    {
        "Name": "태국",
        "Name_ch": "泰国",
        "Name_en": "Thailand",
        "confirmed": 3564,
        "deaths": 59,
        "recovered": 3374
    },
    {
        "Name": "스리랑카",
        "Name_ch": "斯里兰卡",
        "Name_en": "Sri Lanka",
        "confirmed": 3380,
        "deaths": 13,
        "recovered": 3230
    },
    {
        "Name": "에스토니아",
        "Name_ch": "爱沙尼亚",
        "Name_en": "Estonia",
        "confirmed": 3371,
        "deaths": 64,
        "recovered": 2605
    },
    {
        "Name": "Botswana",
        "Name_ch": "",
        "Name_en": "Botswana",
        "confirmed": 3172,
        "deaths": 16,
        "recovered": 710
    },
    {
        "Name": "Mali",
        "Name_ch": "",
        "Name_en": "Mali",
        "confirmed": 3118,
        "deaths": 131,
        "recovered": 2453
    },
    {
        "Name": "Malta",
        "Name_ch": "",
        "Name_en": "Malta",
        "confirmed": 3058,
        "deaths": 35,
        "recovered": 2562
    },
    {
        "Name": "Guyana",
        "Name_ch": "",
        "Name_en": "Guyana",
        "confirmed": 2846,
        "deaths": 78,
        "recovered": 1644
    },
    {
        "Name": "Iceland",
        "Name_ch": "",
        "Name_en": "Iceland",
        "confirmed": 2728,
        "deaths": 10,
        "recovered": 2167
    },
    {
        "Name": "South Sudan",
        "Name_ch": "",
        "Name_en": "South Sudan",
        "confirmed": 2704,
        "deaths": 49,
        "recovered": 1290
    },
    {
        "Name": "Benin",
        "Name_ch": "",
        "Name_en": "Benin",
        "confirmed": 2357,
        "deaths": 41,
        "recovered": 1973
    },
    {
        "Name": "Guinea-Bissau",
        "Name_ch": "",
        "Name_en": "Guinea-Bissau",
        "confirmed": 2324,
        "deaths": 39,
        "recovered": 1549
    },
    {
        "Name": "Sierra Leone",
        "Name_ch": "",
        "Name_en": "Sierra Leone",
        "confirmed": 2231,
        "deaths": 72,
        "recovered": 1687
    },
    {
        "Name": "안도라",
        "Name_ch": "安道尔",
        "Name_en": "Andorra",
        "confirmed": 2050,
        "deaths": 53,
        "recovered": 1432
    },
    {
        "Name": "Yemen",
        "Name_ch": "",
        "Name_en": "Yemen",
        "confirmed": 2034,
        "deaths": 587,
        "recovered": 1286
    },
    {
        "Name": "Uruguay",
        "Name_ch": "",
        "Name_en": "Uruguay",
        "confirmed": 2033,
        "deaths": 48,
        "recovered": 1771
    },
    {
        "Name": "Burkina Faso",
        "Name_ch": "",
        "Name_en": "Burkina Faso",
        "confirmed": 2032,
        "deaths": 58,
        "recovered": 1309
    },
    {
        "Name": "Belize",
        "Name_ch": "",
        "Name_en": "Belize",
        "confirmed": 1943,
        "deaths": 26,
        "recovered": 1225
    },
    {
        "Name": "New Zealand",
        "Name_ch": "",
        "Name_en": "New Zealand",
        "confirmed": 1836,
        "deaths": 25,
        "recovered": 1767
    },
    {
        "Name": "라트비아",
        "Name_ch": "约旦",
        "Name_en": "Latvia",
        "confirmed": 1824,
        "deaths": 37,
        "recovered": 1307
    },
    {
        "Name": "토고",
        "Name_ch": "多哥",
        "Name_en": "Togo",
        "confirmed": 1759,
        "deaths": 48,
        "recovered": 1341
    },
    {
        "Name": "Cyprus",
        "Name_ch": "",
        "Name_en": "Cyprus",
        "confirmed": 1755,
        "deaths": 22,
        "recovered": 1369
    },
    {
        "Name": "French Polynesia",
        "Name_ch": "",
        "Name_en": "French Polynesia",
        "confirmed": 1728,
        "deaths": 7,
        "recovered": 1431
    },
    {
        "Name": "Lesotho",
        "Name_ch": "",
        "Name_en": "Lesotho",
        "confirmed": 1595,
        "deaths": 36,
        "recovered": 873
    },
    {
        "Name": "Martinique",
        "Name_ch": "",
        "Name_en": "Martinique",
        "confirmed": 1543,
        "deaths": 21,
        "recovered": 98
    },
    {
        "Name": "Liberia",
        "Name_ch": "",
        "Name_en": "Liberia",
        "confirmed": 1343,
        "deaths": 82,
        "recovered": 1221
    },
    {
        "Name": "Niger",
        "Name_ch": "",
        "Name_en": "Niger",
        "confirmed": 1196,
        "deaths": 69,
        "recovered": 1110
    },
    {
        "Name": "Chad",
        "Name_ch": "",
        "Name_en": "Chad",
        "confirmed": 1193,
        "deaths": 85,
        "recovered": 1007
    },
    {
        "Name": "베트남",
        "Name_ch": "越南",
        "Name_en": "Vietnam",
        "confirmed": 1094,
        "deaths": 35,
        "recovered": 1010
    },
    {
        "Name": "Sao Tome and Principe",
        "Name_ch": "",
        "Name_en": "Sao Tome and Principe",
        "confirmed": 911,
        "deaths": 15,
        "recovered": 885
    },
    {
        "Name": "산마리노",
        "Name_ch": "圣马力诺",
        "Name_en": "San Marino",
        "confirmed": 732,
        "deaths": 42,
        "recovered": 680
    },
    {
        "Name": "일본크루즈",
        "Name_ch": "日本 邮轮",
        "Name_en": "Diamond Princess",
        "confirmed": 712,
        "deaths": 13,
        "recovered": 651
    },
    {
        "Name": "Turks and Caicos",
        "Name_ch": "",
        "Name_en": "Turks and Caicos",
        "confirmed": 686,
        "deaths": 6,
        "recovered": 642
    },
    {
        "Name": "Channel Islands",
        "Name_ch": "",
        "Name_en": "Channel Islands",
        "confirmed": 664,
        "deaths": 48,
        "recovered": 600
    },
    {
        "Name": "Sint Maarten",
        "Name_ch": "",
        "Name_en": "Sint Maarten",
        "confirmed": 659,
        "deaths": 22,
        "recovered": 557
    },
    {
        "Name": "Papua New Guinea",
        "Name_ch": "",
        "Name_en": "Papua New Guinea",
        "confirmed": 534,
        "deaths": 7,
        "recovered": 516
    },
    {
        "Name": "대만",
        "Name_ch": "台湾",
        "Name_en": "Taiwan",
        "confirmed": 514,
        "deaths": 7,
        "recovered": 483
    },
    {
        "Name": "Tanzania",
        "Name_ch": "",
        "Name_en": "Tanzania",
        "confirmed": 509,
        "deaths": 21,
        "recovered": 183
    },
    {
        "Name": "Burundi",
        "Name_ch": "",
        "Name_en": "Burundi",
        "confirmed": 508,
        "deaths": 1,
        "recovered": 472
    },
    {
        "Name": "Comoros",
        "Name_ch": "",
        "Name_en": "Comoros",
        "confirmed": 479,
        "deaths": 7,
        "recovered": 464
    },
    {
        "Name": "Faeroe Islands",
        "Name_ch": "",
        "Name_en": "Faeroe Islands",
        "confirmed": 467,
        "deaths": 0,
        "recovered": 429
    },
    {
        "Name": "지브롤터",
        "Name_ch": "直布罗陀",
        "Name_en": "Gibraltar",
        "confirmed": 396,
        "deaths": 0,
        "recovered": 344
    },
    {
        "Name": "Curaçao",
        "Name_ch": "",
        "Name_en": "Curaçao",
        "confirmed": 392,
        "deaths": 1,
        "recovered": 171
    },
    {
        "Name": "Saint Martin",
        "Name_ch": "",
        "Name_en": "Saint Martin",
        "confirmed": 383,
        "deaths": 8,
        "recovered": 273
    },
    {
        "Name": "Eritrea",
        "Name_ch": "",
        "Name_en": "Eritrea",
        "confirmed": 375,
        "deaths": 0,
        "recovered": 341
    },
    {
        "Name": "Mauritius",
        "Name_ch": "",
        "Name_en": "Mauritius",
        "confirmed": 367,
        "deaths": 10,
        "recovered": 343
    },
    {
        "Name": "Isle of Man",
        "Name_ch": "",
        "Name_en": "Isle of Man",
        "confirmed": 340,
        "deaths": 24,
        "recovered": 315
    },
    {
        "Name": "Mongolia",
        "Name_ch": "",
        "Name_en": "Mongolia",
        "confirmed": 313,
        "deaths": 0,
        "recovered": 305
    },
    {
        "Name": "부탄",
        "Name_ch": "不丹",
        "Name_en": "Bhutan",
        "confirmed": 281,
        "deaths": 0,
        "recovered": 219
    },
    {
        "Name": "캄보디아",
        "Name_ch": "柬埔寨",
        "Name_en": "Cambodia",
        "confirmed": 277,
        "deaths": 0,
        "recovered": 275
    },
    {
        "Name": "모나코",
        "Name_ch": "摩纳哥",
        "Name_en": "Monaco",
        "confirmed": 218,
        "deaths": 2,
        "recovered": 181
    },
    {
        "Name": "Cayman Islands",
        "Name_ch": "",
        "Name_en": "Cayman Islands",
        "confirmed": 211,
        "deaths": 1,
        "recovered": 208
    },
    {
        "Name": "Barbados",
        "Name_ch": "",
        "Name_en": "Barbados",
        "confirmed": 190,
        "deaths": 7,
        "recovered": 179
    },
    {
        "Name": "Bermuda",
        "Name_ch": "",
        "Name_en": "Bermuda",
        "confirmed": 181,
        "deaths": 9,
        "recovered": 167
    },
    {
        "Name": "Brunei",
        "Name_ch": "",
        "Name_en": "Brunei",
        "confirmed": 146,
        "deaths": 3,
        "recovered": 142
    },
    {
        "Name": "Seychelles",
        "Name_ch": "",
        "Name_en": "Seychelles",
        "confirmed": 143,
        "deaths": 0,
        "recovered": 140
    },
    {
        "Name": "리히텐슈타인",
        "Name_ch": "列支敦士登",
        "Name_en": "Liechtenstein",
        "confirmed": 118,
        "deaths": 1,
        "recovered": 113
    },
    {
        "Name": "Caribbean Netherlands",
        "Name_ch": "",
        "Name_en": "Caribbean Netherlands",
        "confirmed": 106,
        "deaths": 1,
        "recovered": 24
    },
    {
        "Name": "Antigua and Barbuda",
        "Name_ch": "",
        "Name_en": "Antigua and Barbuda",
        "confirmed": 101,
        "deaths": 3,
        "recovered": 92
    },
    {
        "Name": "British Virgin Islands",
        "Name_ch": "",
        "Name_en": "British Virgin Islands",
        "confirmed": 71,
        "deaths": 1,
        "recovered": 66
    },
    {
        "Name": "St. Vincent Grenadines",
        "Name_ch": "",
        "Name_en": "St. Vincent Grenadines",
        "confirmed": 64,
        "deaths": 0,
        "recovered": 64
    },
    {
        "Name": "St. Barth",
        "Name_ch": "",
        "Name_en": "St. Barth",
        "confirmed": 48,
        "deaths": 0,
        "recovered": 25
    },
    {
        "Name": "마카오",
        "Name_ch": "澳门",
        "Name_en": "Macao",
        "confirmed": 46,
        "deaths": 0,
        "recovered": 46
    },
    {
        "Name": "Fiji",
        "Name_ch": "",
        "Name_en": "Fiji",
        "confirmed": 32,
        "deaths": 2,
        "recovered": 28
    },
    {
        "Name": "Dominica",
        "Name_ch": "",
        "Name_en": "Dominica",
        "confirmed": 30,
        "deaths": 0,
        "recovered": 24
    },
    {
        "Name": "Timor-Leste",
        "Name_ch": "",
        "Name_en": "Timor-Leste",
        "confirmed": 28,
        "deaths": 0,
        "recovered": 28
    },
    {
        "Name": "New Caledonia",
        "Name_ch": "",
        "Name_en": "New Caledonia",
        "confirmed": 27,
        "deaths": 0,
        "recovered": 27
    },
    {
        "Name": "Saint Lucia",
        "Name_ch": "",
        "Name_en": "Saint Lucia",
        "confirmed": 27,
        "deaths": 0,
        "recovered": 27
    },
    {
        "Name": "Grenada",
        "Name_ch": "",
        "Name_en": "Grenada",
        "confirmed": 24,
        "deaths": 0,
        "recovered": 24
    },
    {
        "Name": "Laos",
        "Name_ch": "",
        "Name_en": "Laos",
        "confirmed": 23,
        "deaths": 0,
        "recovered": 22
    },
    {
        "Name": "Saint Kitts and Nevis",
        "Name_ch": "",
        "Name_en": "Saint Kitts and Nevis",
        "confirmed": 19,
        "deaths": 0,
        "recovered": 17
    },
    {
        "Name": "Saint Pierre Miquelon",
        "Name_ch": "",
        "Name_en": "Saint Pierre Miquelon",
        "confirmed": 16,
        "deaths": 0,
        "recovered": 6
    },
    {
        "Name": "Greenland",
        "Name_ch": "",
        "Name_en": "Greenland",
        "confirmed": 14,
        "deaths": 0,
        "recovered": 14
    },
    {
        "Name": "Montserrat",
        "Name_ch": "",
        "Name_en": "Montserrat",
        "confirmed": 13,
        "deaths": 1,
        "recovered": 12
    },
    {
        "Name": "Falkland Islands",
        "Name_ch": "",
        "Name_en": "Falkland Islands",
        "confirmed": 13,
        "deaths": 0,
        "recovered": 13
    },
    {
        "Name": "Vatican City",
        "Name_ch": "",
        "Name_en": "Vatican City",
        "confirmed": 12,
        "deaths": 0,
        "recovered": 12
    },
    {
        "Name": "Western Sahara",
        "Name_ch": "",
        "Name_en": "Western Sahara",
        "confirmed": 10,
        "deaths": 1,
        "recovered": 8
    },
    {
        "Name": "MS Zaandam",
        "Name_ch": "",
        "Name_en": "MS Zaandam",
        "confirmed": 9,
        "deaths": 2,
        "recovered": 0
    },
    {
        "Name": "Anguilla",
        "Name_ch": "",
        "Name_en": "Anguilla",
        "confirmed": 3,
        "deaths": 0,
        "recovered": 3
    },
    {
        "Name": "중국",
        "Name_ch": "中国",
        "Name_en": "China",
        "confirmed": 85403,
        "deaths": 4634,
        "recovered": 80578
    }
]