[
    {
        "title": "제주 산방산온천 코로나19 확진자 추가…8명으로 늘어",
        "link": "http://news.khan.co.kr/kh_news/khan_art_view.html?artid=202009102146001&code=620117"
    },
    {
        "title": "코로나19 제주 50번째 확진자 발생",
        "link": "https://www.nocutnews.co.kr/news/5409818"
    },
    {
        "title": "제주서 코로나19 확진자 잇따라 발생…누적 52명",
        "link": "http://yna.kr/AKR20200910178400056?did=1195m"
    },
    {
        "title": "제주도 49번째 코로나 확진자 발생...미국서 입국",
        "link": "http://www.jejusori.net/news/articleView.html?idxno=319920"
    },
    {
        "title": "제주도, 52번째 코로나19 확진자 발생",
        "link": "http://www.nbnnews.co.kr/news/articleView.html?idxno=423746"
    },
    {
        "title": "제주도 이틀새 확진자 4명 발생...'n차 감염' 불안감 확산",
        "link": "http://www.headlinejeju.co.kr/news/articleView.html?idxno=427033"
    },
    {
        "title": "제주 코로나19 감염 51번 52번째 확진자 발생",
        "link": "https://www.pressian.com/pages/articles/2020091023361732420?utm_source=naver&utm_medium=search"
    },
    {
        "title": "네팔 국적 51번째 확진자 접촉자 15명",
        "link": "http://www.jejunews.com/news/articleView.html?idxno=2171527"
    },
    {
        "title": "게스트하우스發 코로나 확진자 추가, 제주 50번째",
        "link": "http://www.newsjeju.net/news/articleView.html?idxno=350305"
    },
    {
        "title": "제주 49번 코로나19 확진자 역학조사 결과 ‘공개’",
        "link": "https://view.asiae.co.kr/article/2020091011192722410"
    }
]